pynecone_helper/__init__.py
pynecone_helper/components/__init__.py
pynecone_helper/components/color_picker.py
pynecone_helper-0.0.1.dist-info/METADATA
pynecone_helper-0.0.1.dist-info/WHEEL
pynecone_helper-0.0.1.dist-info/top_level.txt
pynecone_helper-0.0.1.dist-info/RECORD
