Metadata-Version: 2.1
Name: pynecone-helper
Version: 0.0.1
Summary: Pynecone helper
Home-page: https://github.com/automatethem/pynecone-helper
Author: Sang Ki Kwon
Author-email: automatethem@gmail.com
License: MIT
Platform: UNKNOWN
Requires-Dist: pynecone
